pulseeco/__init__.py
pulseeco/_version.py
pulseeco/constants.py
pulseeco/enums.py
pulseeco/models.py
pulseeco/py.typed
pulseeco/utils.py
pulseeco/api/__init__.py
pulseeco/api/base.py
pulseeco/api/data_types.py
pulseeco/api/http_clients.py
pulseeco/api/pulse_eco_api.py
pulseeco/client/__init__.py
pulseeco/client/client.py
pulseeco/client/enums.py
pulseeco/client/models.py
pulse_eco-2.3.3.dist-info/METADATA
pulse_eco-2.3.3.dist-info/WHEEL
pulse_eco-2.3.3.dist-info/licenses/LICENSE
pulse_eco-2.3.3.dist-info/RECORD
