Metadata-Version: 2.1
Name: pulse-eco
Version: 2.3.3
Summary: pulse.eco API wrapper
Project-URL: Bug Tracker, https://github.com/martinkozle/pulse-eco/issues
Project-URL: Homepage, https://github.com/martinkozle/pulse-eco
Author-email: martinkozle <martinkozle@yahoo.com>
License-Expression: MIT
License-File: LICENSE
Keywords: air,air pollution,air quality index,api,aqi,eco,pollution,pulse,pulse.eco,python,quality,wrapper
Classifier: Development Status :: 5 - Production/Stable
Classifier: Framework :: Pydantic
Classifier: License :: OSI Approved :: MIT License
Classifier: Natural Language :: English
Classifier: Operating System :: OS Independent
Classifier: Programming Language :: Python
Classifier: Programming Language :: Python :: 3
Classifier: Topic :: Scientific/Engineering :: Atmospheric Science
Classifier: Topic :: Scientific/Engineering :: Information Analysis
Classifier: Topic :: Software Development
Classifier: Topic :: Software Development :: Libraries
Classifier: Topic :: Software Development :: Libraries :: Python Modules
Classifier: Typing :: Typed
Requires-Python: >=3.8
Provides-Extra: aiohttp
Requires-Dist: aiohttp>=3.9.0; extra == 'aiohttp'
Provides-Extra: all-http
Requires-Dist: pulse-eco[aiohttp,httpx,requests]; extra == 'all-http'
Provides-Extra: client
Requires-Dist: pydantic<3,>=2; extra == 'client'
Provides-Extra: dev
Requires-Dist: ipython; extra == 'dev'
Requires-Dist: pip-tools>=7.3.0; extra == 'dev'
Requires-Dist: pre-commit>=3.5.0; extra == 'dev'
Requires-Dist: pulse-eco[all-http,client,docs,lint,test]; extra == 'dev'
Provides-Extra: docs
Requires-Dist: mkdocs; extra == 'docs'
Requires-Dist: mkdocs-material; extra == 'docs'
Requires-Dist: mkdocstrings[python]; extra == 'docs'
Requires-Dist: pymdown-extensions; extra == 'docs'
Provides-Extra: httpx
Requires-Dist: httpx>=0.25.1; extra == 'httpx'
Provides-Extra: lint
Requires-Dist: mypy~=1.8.0; extra == 'lint'
Requires-Dist: pulse-eco[all-http,client,types]; extra == 'lint'
Requires-Dist: ruff==0.3.2; extra == 'lint'
Provides-Extra: requests
Requires-Dist: requests>=2.31.0; extra == 'requests'
Provides-Extra: test
Requires-Dist: coverage[toml]~=7.3.4; extra == 'test'
Requires-Dist: pulse-eco[all-http,client]; extra == 'test'
Requires-Dist: pytest-asyncio~=0.23.5; extra == 'test'
Requires-Dist: pytest~=8.1.1; extra == 'test'
Requires-Dist: python-dotenv~=1.0.0; extra == 'test'
Provides-Extra: types
Requires-Dist: types-requests>=2.31.0; extra == 'types'
